ccmplots/__init__.py
ccmplots/styles/ccm.mplstyle
ccmplots/styles/customization/1x2_1col.mplstyle
ccmplots/styles/customization/1x3.mplstyle
ccmplots/styles/customization/1x4.mplstyle
ccmplots/styles/customization/a4.mplstyle
ccmplots/styles/customization/bw_palette.mplstyle
ccmplots/styles/customization/daniel_style.mplstyle
ccmplots/styles/customization/font10pt.mplstyle
ccmplots/styles/customization/font11pt.mplstyle
ccmplots/styles/customization/font8pt.mplstyle
ccmplots/styles/customization/large_rect.mplstyle
ccmplots/styles/customization/no-latex.mplstyle
ccmplots/styles/customization/sans.mplstyle
ccmplots/styles/customization/square.mplstyle
ccmplots/styles/customization/tab10scatter.mplstyle
ccmplots/styles/customization/tab20.mplstyle
ccmplots/styles/customization/tab20scatter.mplstyle
ccmplots/styles/customization/tum4c.mplstyle
ccmplots-0.1.14.dist-info/METADATA
ccmplots-0.1.14.dist-info/WHEEL
ccmplots-0.1.14.dist-info/top_level.txt
ccmplots-0.1.14.dist-info/RECORD
