Metadata-Version: 2.4
Name: ccmplots
Version: 0.1.14
Requires-Dist: requests
Requires-Dist: importlib-metadata; python_version < "3.8"
